xattr/lib_build.c
xattr/__init__.py
xattr/lib_build.h
xattr/lib.py
xattr/pyxattr_compat.py
xattr/lib_build.py
xattr/tool.py
xattr/_lib.pypy310-pp73-x86_64-linux-gnu.so
xattr-1.2.0.dist-info/entry_points.txt
xattr-1.2.0.dist-info/METADATA
xattr-1.2.0.dist-info/RECORD
xattr-1.2.0.dist-info/top_level.txt
xattr-1.2.0.dist-info/WHEEL
xattr-1.2.0.dist-info/licenses/LICENSE.txt
