Metadata-Version: 2.1
Name: xattr
Version: 1.2.0
Summary: Python wrapper for extended filesystem attributes
Author-email: Bob Ippolito <bob@redivi.com>
Maintainer-email: Bob Ippolito <bob@redivi.com>
License: This is the MIT license.  This software may also be distributed under the same terms as Python (the PSF license).
Project-URL: Homepage, https://github.com/xattr/xattr
Project-URL: Repository, https://github.com/xattr/xattr
Keywords: xattr
Platform: MacOS X
Platform: Linux
Platform: FreeBSD
Platform: Solaris
Classifier: Environment :: Console
Classifier: Intended Audience :: Developers
Classifier: License :: OSI Approved :: MIT License
Classifier: Natural Language :: English
Classifier: Operating System :: MacOS :: MacOS X
Classifier: Operating System :: POSIX :: Linux
Classifier: Operating System :: POSIX :: BSD :: FreeBSD
Classifier: Operating System :: POSIX :: SunOS/Solaris
Classifier: Programming Language :: Python
Classifier: Programming Language :: Python :: 3
Classifier: Topic :: Software Development :: Libraries :: Python Modules
Requires-Python: >=3.8
License-File: LICENSE.txt
Requires-Dist: cffi>=1.16.0
Provides-Extra: test
Requires-Dist: pytest; extra == "test"
